Metadata-Version: 1.0
Name: mmal
Version: 0.0.2
Summary: Meteorological Middleware Application Layer
Home-page: https://github.com/hodgesds/mmal-python
Author: Daniel Hodges
Author-email: hodges.daniel.scott@gmail.com
License: UNKNOWN
Platform: UNKNOWN
